glycorender/__init__.py
glycorender/render.py
glycorender/fonts/Comfortaa-Bold.ttf
glycorender/fonts/Comfortaa-Regular.ttf
glycorender-0.2.3.dist-info/licenses/LICENSE
glycorender-0.2.3.dist-info/METADATA
glycorender-0.2.3.dist-info/WHEEL
glycorender-0.2.3.dist-info/top_level.txt
glycorender-0.2.3.dist-info/RECORD
