Metadata-Version: 2.4
Name: glycorender
Version: 0.2.3
Summary: A bespoke SVG to PDF/PNG renderer for the GlycoDraw platform
Author-email: Daniel Bojar <daniel.bojar@gu.se>
License: MIT
Project-URL: Homepage, https://github.com/BojarLab/glycorender
Project-URL: Bug Tracker, https://github.com/BojarLab/glycorender/issues
Keywords: svg,pdf,renderer,glycans,chemistry,glycodraw
Classifier: Programming Language :: Python :: 3
Classifier: License :: OSI Approved :: MIT License
Classifier: Operating System :: OS Independent
Classifier: Topic :: Scientific/Engineering :: Chemistry
Classifier: Topic :: Multimedia :: Graphics :: Graphics Conversion
Requires-Python: >=3.9
License-File: LICENSE
Requires-Dist: reportlab>=3.6.0
Requires-Dist: Pillow
Provides-Extra: png
Requires-Dist: pymupdf>=1.19.0; extra == "png"
Dynamic: license-file
